{
  "cli": {
    "version": ">= 5.0.0",
    "appVersionSource": "remote"
  },
  "build": {
    "development": {
      "developmentClient": true,
      "distribution": "internal",
      "android": {
        "buildType": "apk",
        "gradleCommand": ":app:assembleDebug"
      },
      "ios": {
        "simulator": false
      },
      "env": {
        "APP_ENV": "development"
      },
      "channel": "development"
    },
    "preview": {
      "distribution": "internal",
      "android": {
        "buildType": "apk"
      },
      "env": {
        "APP_ENV": "preview"
      },
      "channel": "preview"
    },
    "production": {
      "android": {
        "buildType": "apk"
      },
      "env": {
        "APP_ENV": "production"
      },
      "channel": "production"
    }
  },
  "submit": {
    "production": {
      "android": {
        "serviceAccountKeyPath": "./google-play-key.json",
        "track": "internal"
      },
      "ios": {
        "appleId": "your@apple.com",
        "ascAppId": "your-app-store-connect-app-id",
        "appleTeamId": "YOUR_TEAM_ID"
      }
    }
  }
}
